backupdir/__init__.py
backupdir/backupdir.py
backupdir-1.0.0.dist-info/LICENSE
backupdir-1.0.0.dist-info/METADATA
backupdir-1.0.0.dist-info/WHEEL
backupdir-1.0.0.dist-info/top_level.txt
backupdir-1.0.0.dist-info/RECORD
