Metadata-Version: 2.1
Name: backupdir
Version: 1.0.0
Summary: Python script copies the source directory (with all files and subdirectories) to the specified location and zips it.
Home-page: https://github.com/IgorMan2005/backupdir
Author: IgorMan (IgorMan2005)
Author-email: igorman2005@gmail.com
Project-URL: Documentation, https://best-itpro.ru/news/backupdir/
Keywords: python backupdir backup foder zip archive
Classifier: Programming Language :: Python :: 3.9
Classifier: License :: OSI Approved :: MIT License
Classifier: Operating System :: OS Independent
Requires-Python: >=3.6
License-File: LICENSE
